phast/__init__.py
phast/embedding.py
phast/graph_rewiring.py
phast/utils.py
phast-0.1.3.dist-info/LICENSE
phast-0.1.3.dist-info/METADATA
phast-0.1.3.dist-info/WHEEL
phast-0.1.3.dist-info/RECORD
