Metadata-Version: 2.3
Name: phast
Version: 0.1.3
Summary: 
License: MIT
Author: Victor Schmidt
Author-email: vsch@pm.me
Requires-Python: >=3.8.1,<3.14
Classifier: License :: OSI Approved :: MIT License
Classifier: Programming Language :: Python :: 3
Classifier: Programming Language :: Python :: 3.9
Classifier: Programming Language :: Python :: 3.10
Classifier: Programming Language :: Python :: 3.11
Classifier: Programming Language :: Python :: 3.12
Classifier: Programming Language :: Python :: 3.13
Requires-Dist: mendeleev (>=0.12.1)
Requires-Dist: pandas (>=1.4)
Requires-Dist: pyyaml (>=6.0.2)
Requires-Dist: torch (>=1.11)
